xj_favorite/__init__.py
xj_favorite/admin.py
xj_favorite/apis.py
xj_favorite/apps.py
xj_favorite/models.py
xj_favorite/serializers.py
xj_favorite/services.py
xj_favorite/tests.py
xj_favorite/urls.py
xj_favorite/views.py
xj_favorite/api/__init__.py
xj_favorite/api/favorite_list.py
xj_favorite/utils/__init__.py
xj_favorite/utils/custom_response.py
xj_favorite-1.0.6.dist-info/METADATA
xj_favorite-1.0.6.dist-info/WHEEL
xj_favorite-1.0.6.dist-info/top_level.txt
xj_favorite-1.0.6.dist-info/RECORD
